{"nodes": [{"id": "d_propackhub_apps_estimation_studio_docs_es_memory_md", "label": "ES_MEMORY.md", "file_type": "document", "source_file": "docs/ES_MEMORY.md", "source_location": "L1"}, {"id": "docs_es_memory_propackhub_estimation_studio_project_memory", "label": "ProPackHub Estimation Studio \u2014 Project Memory", "file_type": "document", "source_file": "docs/ES_MEMORY.md", "source_location": "L1"}, {"id": "docs_es_memory_canonical_docs_read_order", "label": "Canonical docs (read order)", "file_type": "document", "source_file": "docs/ES_MEMORY.md", "source_location": "L9"}, {"id": "docs_es_memory_product_identity_fixed", "label": "Product identity (fixed)", "file_type": "document", "source_file": "docs/ES_MEMORY.md", "source_location": "L26"}, {"id": "docs_es_memory_costing_rules_locked", "label": "Costing rules (locked)", "file_type": "document", "source_file": "docs/ES_MEMORY.md", "source_location": "L36"}, {"id": "docs_es_memory_layer_types_laravel", "label": "Layer types (Laravel)", "file_type": "document", "source_file": "docs/ES_MEMORY.md", "source_location": "L38"}, {"id": "docs_es_memory_ink_systems_not_color_specific", "label": "Ink systems (not color-specific)", "file_type": "document", "source_file": "docs/ES_MEMORY.md", "source_location": "L42"}, {"id": "docs_es_memory_adhesive", "label": "Adhesive", "file_type": "document", "source_file": "docs/ES_MEMORY.md", "source_location": "L53"}, {"id": "docs_es_memory_microns", "label": "Microns", "file_type": "document", "source_file": "docs/ES_MEMORY.md", "source_location": "L59"}, {"id": "docs_es_memory_sale_price_laravel_additive", "label": "Sale price (Laravel additive)", "file_type": "document", "source_file": "docs/ES_MEMORY.md", "source_location": "L63"}, {"id": "docs_es_memory_dimensions_decision_21", "label": "Dimensions (Decision #21)", "file_type": "document", "source_file": "docs/ES_MEMORY.md", "source_location": "L71"}, {"id": "docs_es_memory_currency_decision_22", "label": "Currency (Decision #22)", "file_type": "document", "source_file": "docs/ES_MEMORY.md", "source_location": "L86"}, {"id": "docs_es_memory_client_side_engine_decision_23", "label": "Client-side engine (Decision #23)", "file_type": "document", "source_file": "docs/ES_MEMORY.md", "source_location": "L94"}, {"id": "docs_es_memory_external_audit_folded_into_prd_v3_4", "label": "External audit (folded into PRD v3.4)", "file_type": "document", "source_file": "docs/ES_MEMORY.md", "source_location": "L100"}, {"id": "docs_es_memory_operations", "label": "Operations", "file_type": "document", "source_file": "docs/ES_MEMORY.md", "source_location": "L109"}, {"id": "docs_es_memory_cost_visibility_decision_20_sales_rep_default", "label": "Cost visibility (Decision #20 \u2014 sales rep default)", "file_type": "document", "source_file": "docs/ES_MEMORY.md", "source_location": "L113"}, {"id": "docs_es_memory_mobile_decision_8_20", "label": "Mobile (Decision #8 + #20)", "file_type": "document", "source_file": "docs/ES_MEMORY.md", "source_location": "L121"}, {"id": "docs_es_memory_laminate_stacks_locked", "label": "Laminate stacks (locked)", "file_type": "document", "source_file": "docs/ES_MEMORY.md", "source_location": "L127"}, {"id": "docs_es_memory_standard_templates", "label": "Standard templates", "file_type": "document", "source_file": "docs/ES_MEMORY.md", "source_location": "L139"}, {"id": "docs_es_memory_build_sequence_owner_one_step_at_a_time", "label": "Build sequence (owner: one step at a time)", "file_type": "document", "source_file": "docs/ES_MEMORY.md", "source_location": "L147"}, {"id": "docs_es_memory_session_log", "label": "Session log", "file_type": "document", "source_file": "docs/ES_MEMORY.md", "source_location": "L162"}, {"id": "docs_es_memory_2026_06_11_prd_platform_scope", "label": "2026-06-11 \u2014 PRD + platform scope", "file_type": "document", "source_file": "docs/ES_MEMORY.md", "source_location": "L164"}, {"id": "docs_es_memory_2026_06_12_laravel_deep_audit", "label": "2026-06-12 \u2014 Laravel deep audit", "file_type": "document", "source_file": "docs/ES_MEMORY.md", "source_location": "L171"}, {"id": "docs_es_memory_2026_06_12_ink_sb_uv_laminate_alu", "label": "2026-06-12 \u2014 Ink SB / UV + laminate Alu", "file_type": "document", "source_file": "docs/ES_MEMORY.md", "source_location": "L177"}, {"id": "docs_es_memory_2026_06_12_printing_web_class_decision_19", "label": "2026-06-12 \u2014 Printing web class (Decision #19)", "file_type": "document", "source_file": "docs/ES_MEMORY.md", "source_location": "L183"}, {"id": "docs_es_memory_2026_06_11_external_audit_prd_v3_4", "label": "2026-06-11 \u2014 External audit \u2192 PRD v3.4", "file_type": "document", "source_file": "docs/ES_MEMORY.md", "source_location": "L190"}, {"id": "docs_es_memory_2026_06_11_global_currency_decision_22", "label": "2026-06-11 \u2014 Global currency (Decision #22)", "file_type": "document", "source_file": "docs/ES_MEMORY.md", "source_location": "L195"}, {"id": "docs_es_memory_2026_06_11_dimensions_audit_decision_21", "label": "2026-06-11 \u2014 Dimensions audit (Decision #21)", "file_type": "document", "source_file": "docs/ES_MEMORY.md", "source_location": "L201"}, {"id": "docs_es_memory_2026_06_12_cost_visibility_mobile_decision_20", "label": "2026-06-12 \u2014 Cost visibility + mobile (Decision #20)", "file_type": "document", "source_file": "docs/ES_MEMORY.md", "source_location": "L208"}, {"id": "docs_es_memory_2026_06_12_audit_handoff_mobile_mockup", "label": "2026-06-12 \u2014 Audit handoff + mobile mockup", "file_type": "document", "source_file": "docs/ES_MEMORY.md", "source_location": "L214"}, {"id": "docs_es_memory_2026_06_14_workspace_memory_doc_fixes", "label": "2026-06-14 \u2014 Workspace memory + doc fixes", "file_type": "document", "source_file": "docs/ES_MEMORY.md", "source_location": "L234"}, {"id": "docs_es_memory_session_log_2026_06_17", "label": "Session log \u2014 2026-06-17", "file_type": "document", "source_file": "docs/ES_MEMORY.md", "source_location": "L248"}, {"id": "docs_es_memory_fixes_7_10_applied", "label": "Fixes 7-10 applied", "file_type": "document", "source_file": "docs/ES_MEMORY.md", "source_location": "L250"}, {"id": "docs_es_memory_open_items", "label": "Open items", "file_type": "document", "source_file": "docs/ES_MEMORY.md", "source_location": "L261"}, {"id": "docs_es_memory_2026_06_14_implementation_scaffold_started", "label": "2026-06-14 \u2014 Implementation Scaffold Started", "file_type": "document", "source_file": "docs/ES_MEMORY.md", "source_location": "L278"}, {"id": "docs_es_memory_2026_06_14_windows_startup_scripts_added", "label": "2026-06-14 \u2014 Windows Startup Scripts Added", "file_type": "document", "source_file": "docs/ES_MEMORY.md", "source_location": "L300"}, {"id": "docs_es_memory_2026_06_14_full_backend_implementation_complete", "label": "2026-06-14 \u2014 Full Backend Implementation Complete", "file_type": "document", "source_file": "docs/ES_MEMORY.md", "source_location": "L311"}, {"id": "docs_es_memory_2026_06_15_critical_bug_fixes_6_major_issues", "label": "2026-06-15 \u2014 Critical Bug Fixes (6 major issues)", "file_type": "document", "source_file": "docs/ES_MEMORY.md", "source_location": "L350"}, {"id": "docs_es_memory_2026_06_15_missing_estimate_crud_endpoints_added", "label": "2026-06-15 \u2014 Missing Estimate CRUD Endpoints Added", "file_type": "document", "source_file": "docs/ES_MEMORY.md", "source_location": "L377"}, {"id": "docs_es_memory_2026_06_15_master_materials_library_seeding", "label": "2026-06-15 \u2014 Master Materials Library Seeding", "file_type": "document", "source_file": "docs/ES_MEMORY.md", "source_location": "L401"}, {"id": "docs_es_memory_2026_06_15_full_implementation_audit_code_vs_prd", "label": "2026-06-15 \u2014 Full implementation audit (code vs PRD)", "file_type": "document", "source_file": "docs/ES_MEMORY.md", "source_location": "L422"}, {"id": "docs_es_memory_2026_06_16_phase_a_phase_b_complete", "label": "2026-06-16 \u2014 Phase A + Phase B complete", "file_type": "document", "source_file": "docs/ES_MEMORY.md", "source_location": "L460"}, {"id": "docs_es_memory_2026_06_17_phase_d_phase_e_partial_phase_b_re_merge", "label": "2026-06-17 \u2014 Phase D + Phase E partial + Phase B re-merge", "file_type": "document", "source_file": "docs/ES_MEMORY.md", "source_location": "L506"}], "edges": [{"source": "d_propackhub_apps_estimation_studio_docs_es_memory_md", "target": "docs_es_memory_propackhub_estimation_studio_project_memory", "relation": "contains", "confidence": "EXTRACTED", "source_file": "docs/ES_MEMORY.md", "source_location": "L1", "weight": 1.0}, {"source": "docs_es_memory_propackhub_estimation_studio_project_memory", "target": "docs_es_memory_canonical_docs_read_order", "relation": "contains", "confidence": "EXTRACTED", "source_file": "docs/ES_MEMORY.md", "source_location": "L9", "weight": 1.0}, {"source": "docs_es_memory_propackhub_estimation_studio_project_memory", "target": "docs_es_memory_product_identity_fixed", "relation": "contains", "confidence": "EXTRACTED", "source_file": "docs/ES_MEMORY.md", "source_location": "L26", "weight": 1.0}, {"source": "docs_es_memory_propackhub_estimation_studio_project_memory", "target": "docs_es_memory_costing_rules_locked", "relation": "contains", "confidence": "EXTRACTED", "source_file": "docs/ES_MEMORY.md", "source_location": "L36", "weight": 1.0}, {"source": "docs_es_memory_costing_rules_locked", "target": "docs_es_memory_layer_types_laravel", "relation": "contains", "confidence": "EXTRACTED", "source_file": "docs/ES_MEMORY.md", "source_location": "L38", "weight": 1.0}, {"source": "docs_es_memory_costing_rules_locked", "target": "docs_es_memory_ink_systems_not_color_specific", "relation": "contains", "confidence": "EXTRACTED", "source_file": "docs/ES_MEMORY.md", "source_location": "L42", "weight": 1.0}, {"source": "docs_es_memory_costing_rules_locked", "target": "docs_es_memory_adhesive", "relation": "contains", "confidence": "EXTRACTED", "source_file": "docs/ES_MEMORY.md", "source_location": "L53", "weight": 1.0}, {"source": "docs_es_memory_costing_rules_locked", "target": "docs_es_memory_microns", "relation": "contains", "confidence": "EXTRACTED", "source_file": "docs/ES_MEMORY.md", "source_location": "L59", "weight": 1.0}, {"source": "docs_es_memory_costing_rules_locked", "target": "docs_es_memory_sale_price_laravel_additive", "relation": "contains", "confidence": "EXTRACTED", "source_file": "docs/ES_MEMORY.md", "source_location": "L63", "weight": 1.0}, {"source": "docs_es_memory_costing_rules_locked", "target": "docs_es_memory_dimensions_decision_21", "relation": "contains", "confidence": "EXTRACTED", "source_file": "docs/ES_MEMORY.md", "source_location": "L71", "weight": 1.0}, {"source": "docs_es_memory_costing_rules_locked", "target": "docs_es_memory_currency_decision_22", "relation": "contains", "confidence": "EXTRACTED", "source_file": "docs/ES_MEMORY.md", "source_location": "L86", "weight": 1.0}, {"source": "docs_es_memory_costing_rules_locked", "target": "docs_es_memory_client_side_engine_decision_23", "relation": "contains", "confidence": "EXTRACTED", "source_file": "docs/ES_MEMORY.md", "source_location": "L94", "weight": 1.0}, {"source": "docs_es_memory_costing_rules_locked", "target": "docs_es_memory_external_audit_folded_into_prd_v3_4", "relation": "contains", "confidence": "EXTRACTED", "source_file": "docs/ES_MEMORY.md", "source_location": "L100", "weight": 1.0}, {"source": "docs_es_memory_costing_rules_locked", "target": "docs_es_memory_operations", "relation": "contains", "confidence": "EXTRACTED", "source_file": "docs/ES_MEMORY.md", "source_location": "L109", "weight": 1.0}, {"source": "docs_es_memory_costing_rules_locked", "target": "docs_es_memory_cost_visibility_decision_20_sales_rep_default", "relation": "contains", "confidence": "EXTRACTED", "source_file": "docs/ES_MEMORY.md", "source_location": "L113", "weight": 1.0}, {"source": "docs_es_memory_costing_rules_locked", "target": "docs_es_memory_mobile_decision_8_20", "relation": "contains", "confidence": "EXTRACTED", "source_file": "docs/ES_MEMORY.md", "source_location": "L121", "weight": 1.0}, {"source": "docs_es_memory_propackhub_estimation_studio_project_memory", "target": "docs_es_memory_laminate_stacks_locked", "relation": "contains", "confidence": "EXTRACTED", "source_file": "docs/ES_MEMORY.md", "source_location": "L127", "weight": 1.0}, {"source": "docs_es_memory_propackhub_estimation_studio_project_memory", "target": "docs_es_memory_standard_templates", "relation": "contains", "confidence": "EXTRACTED", "source_file": "docs/ES_MEMORY.md", "source_location": "L139", "weight": 1.0}, {"source": "docs_es_memory_propackhub_estimation_studio_project_memory", "target": "docs_es_memory_build_sequence_owner_one_step_at_a_time", "relation": "contains", "confidence": "EXTRACTED", "source_file": "docs/ES_MEMORY.md", "source_location": "L147", "weight": 1.0}, {"source": "docs_es_memory_propackhub_estimation_studio_project_memory", "target": "docs_es_memory_session_log", "relation": "contains", "confidence": "EXTRACTED", "source_file": "docs/ES_MEMORY.md", "source_location": "L162", "weight": 1.0}, {"source": "docs_es_memory_session_log", "target": "docs_es_memory_2026_06_11_prd_platform_scope", "relation": "contains", "confidence": "EXTRACTED", "source_file": "docs/ES_MEMORY.md", "source_location": "L164", "weight": 1.0}, {"source": "docs_es_memory_session_log", "target": "docs_es_memory_2026_06_12_laravel_deep_audit", "relation": "contains", "confidence": "EXTRACTED", "source_file": "docs/ES_MEMORY.md", "source_location": "L171", "weight": 1.0}, {"source": "docs_es_memory_session_log", "target": "docs_es_memory_2026_06_12_ink_sb_uv_laminate_alu", "relation": "contains", "confidence": "EXTRACTED", "source_file": "docs/ES_MEMORY.md", "source_location": "L177", "weight": 1.0}, {"source": "docs_es_memory_session_log", "target": "docs_es_memory_2026_06_12_printing_web_class_decision_19", "relation": "contains", "confidence": "EXTRACTED", "source_file": "docs/ES_MEMORY.md", "source_location": "L183", "weight": 1.0}, {"source": "docs_es_memory_session_log", "target": "docs_es_memory_2026_06_11_external_audit_prd_v3_4", "relation": "contains", "confidence": "EXTRACTED", "source_file": "docs/ES_MEMORY.md", "source_location": "L190", "weight": 1.0}, {"source": "docs_es_memory_session_log", "target": "docs_es_memory_2026_06_11_global_currency_decision_22", "relation": "contains", "confidence": "EXTRACTED", "source_file": "docs/ES_MEMORY.md", "source_location": "L195", "weight": 1.0}, {"source": "docs_es_memory_session_log", "target": "docs_es_memory_2026_06_11_dimensions_audit_decision_21", "relation": "contains", "confidence": "EXTRACTED", "source_file": "docs/ES_MEMORY.md", "source_location": "L201", "weight": 1.0}, {"source": "docs_es_memory_session_log", "target": "docs_es_memory_2026_06_12_cost_visibility_mobile_decision_20", "relation": "contains", "confidence": "EXTRACTED", "source_file": "docs/ES_MEMORY.md", "source_location": "L208", "weight": 1.0}, {"source": "docs_es_memory_session_log", "target": "docs_es_memory_2026_06_12_audit_handoff_mobile_mockup", "relation": "contains", "confidence": "EXTRACTED", "source_file": "docs/ES_MEMORY.md", "source_location": "L214", "weight": 1.0}, {"source": "docs_es_memory_session_log", "target": "docs_es_memory_2026_06_14_workspace_memory_doc_fixes", "relation": "contains", "confidence": "EXTRACTED", "source_file": "docs/ES_MEMORY.md", "source_location": "L234", "weight": 1.0}, {"source": "docs_es_memory_propackhub_estimation_studio_project_memory", "target": "docs_es_memory_session_log_2026_06_17", "relation": "contains", "confidence": "EXTRACTED", "source_file": "docs/ES_MEMORY.md", "source_location": "L248", "weight": 1.0}, {"source": "docs_es_memory_session_log_2026_06_17", "target": "docs_es_memory_fixes_7_10_applied", "relation": "contains", "confidence": "EXTRACTED", "source_file": "docs/ES_MEMORY.md", "source_location": "L250", "weight": 1.0}, {"source": "docs_es_memory_propackhub_estimation_studio_project_memory", "target": "docs_es_memory_open_items", "relation": "contains", "confidence": "EXTRACTED", "source_file": "docs/ES_MEMORY.md", "source_location": "L261", "weight": 1.0}, {"source": "docs_es_memory_open_items", "target": "docs_es_memory_2026_06_14_implementation_scaffold_started", "relation": "contains", "confidence": "EXTRACTED", "source_file": "docs/ES_MEMORY.md", "source_location": "L278", "weight": 1.0}, {"source": "docs_es_memory_open_items", "target": "docs_es_memory_2026_06_14_windows_startup_scripts_added", "relation": "contains", "confidence": "EXTRACTED", "source_file": "docs/ES_MEMORY.md", "source_location": "L300", "weight": 1.0}, {"source": "docs_es_memory_open_items", "target": "docs_es_memory_2026_06_14_full_backend_implementation_complete", "relation": "contains", "confidence": "EXTRACTED", "source_file": "docs/ES_MEMORY.md", "source_location": "L311", "weight": 1.0}, {"source": "docs_es_memory_open_items", "target": "docs_es_memory_2026_06_15_critical_bug_fixes_6_major_issues", "relation": "contains", "confidence": "EXTRACTED", "source_file": "docs/ES_MEMORY.md", "source_location": "L350", "weight": 1.0}, {"source": "docs_es_memory_open_items", "target": "docs_es_memory_2026_06_15_missing_estimate_crud_endpoints_added", "relation": "contains", "confidence": "EXTRACTED", "source_file": "docs/ES_MEMORY.md", "source_location": "L377", "weight": 1.0}, {"source": "docs_es_memory_open_items", "target": "docs_es_memory_2026_06_15_master_materials_library_seeding", "relation": "contains", "confidence": "EXTRACTED", "source_file": "docs/ES_MEMORY.md", "source_location": "L401", "weight": 1.0}, {"source": "docs_es_memory_open_items", "target": "docs_es_memory_2026_06_15_full_implementation_audit_code_vs_prd", "relation": "contains", "confidence": "EXTRACTED", "source_file": "docs/ES_MEMORY.md", "source_location": "L422", "weight": 1.0}, {"source": "docs_es_memory_open_items", "target": "docs_es_memory_2026_06_16_phase_a_phase_b_complete", "relation": "contains", "confidence": "EXTRACTED", "source_file": "docs/ES_MEMORY.md", "source_location": "L460", "weight": 1.0}, {"source": "docs_es_memory_open_items", "target": "docs_es_memory_2026_06_17_phase_d_phase_e_partial_phase_b_re_merge", "relation": "contains", "confidence": "EXTRACTED", "source_file": "docs/ES_MEMORY.md", "source_location": "L506", "weight": 1.0}], "input_tokens": 0, "output_tokens": 0}